xadix/__init__.py
xadix/cloudflare/__init__.py
xadix/cloudflare/_version.py
xadix/cloudflare/cli.py
xadix_cloudflare-0.1.0.dist-info/METADATA
xadix_cloudflare-0.1.0.dist-info/WHEEL
xadix_cloudflare-0.1.0.dist-info/entry_points.txt
xadix_cloudflare-0.1.0.dist-info/top_level.txt
xadix_cloudflare-0.1.0.dist-info/RECORD
